chut/__init__.py
chut/recipe.py
chut/scripts.py
chut/examples/__init__.py
chut/examples/examples.py
chut/examples/github_clone.py
chut/examples/rfsync.py
chut/examples/ssh_copy_id.py
chut/examples/ssh_mount.py
chut/examples/sudo.py
chut/examples/vlserie.py
chut/examples/webapp.py
chut-0.18.dist-info/METADATA
chut-0.18.dist-info/WHEEL
chut-0.18.dist-info/entry_points.txt
chut-0.18.dist-info/top_level.txt
chut-0.18.dist-info/RECORD
