Metadata-Version: 2.1
Name: chut
Version: 0.18
Summary: Small tool to interact with shell and pipes
Home-page: https://github.com/gawel/chut/
Author: Gael Pasgrimaud
Author-email: gael@gawel.org
License: MIT
Keywords: sh shell bash
Platform: UNKNOWN
Classifier: Intended Audience :: Developers
Classifier: License :: OSI Approved :: MIT License
Classifier: Operating System :: POSIX
Classifier: Programming Language :: Unix Shell
Classifier: Programming Language :: Python :: 3
Requires-Dist: docopt
Requires-Dist: ConfigObject
